mistralai_workflows/plugins/agents/__init__.py
mistralai_workflows/plugins/agents/agent.py
mistralai_workflows/plugins/agents/mcp.py
mistralai_workflows/plugins/agents/runner.py
mistralai_workflows/plugins/agents/tool.py
mistralai_workflows/plugins/agents/examples/__init__.py
mistralai_workflows/plugins/agents/examples/workflow_local_session_streaming.py
mistralai_workflows/plugins/agents/examples/workflow_travel_agent_streaming.py
mistralai_workflows/plugins/agents/examples/workflow_with_agent.py
mistralai_workflows/plugins/agents/session/__init__.py
mistralai_workflows/plugins/agents/session/local_session.py
mistralai_workflows/plugins/agents/session/remote_session.py
mistralai_workflows/plugins/agents/session/session.py
mistralai_workflows_plugins_agents-2.0.0rc12.dist-info/METADATA
mistralai_workflows_plugins_agents-2.0.0rc12.dist-info/WHEEL
mistralai_workflows_plugins_agents-2.0.0rc12.dist-info/licenses/LICENSE
mistralai_workflows_plugins_agents-2.0.0rc12.dist-info/RECORD
